binarystarsolve/__init__.py
binarystarsolve/binarystarsolve.py
BinaryStarSolver-1.2.0.dist-info/LICENSE
BinaryStarSolver-1.2.0.dist-info/METADATA
BinaryStarSolver-1.2.0.dist-info/WHEEL
BinaryStarSolver-1.2.0.dist-info/top_level.txt
BinaryStarSolver-1.2.0.dist-info/RECORD
