Metadata-Version: 2.1
Name: BinaryStarSolver
Version: 1.2.0
Summary: Solves for the orbital elements of binary stars, given radial velocity time series
Home-page: https://github.com/NickMilsonPhysics/binarystarsolve
Author: Nicholas Milson
Author-email: nick.milson@dal.ca
License: UNKNOWN
Platform: UNKNOWN
Classifier: Programming Language :: Python :: 3.7
Classifier: License :: OSI Approved :: GNU General Public License v3 (GPLv3)
Requires-Python: >=3.6
